eve_netease_api/__init__.py
eve_netease_api/api_client.py
eve_netease_api/configuration.py
eve_netease_api/rest.py
eve_netease_api/api/__init__.py
eve_netease_api/api/alliance_api.py
eve_netease_api/api/assets_api.py
eve_netease_api/api/bookmarks_api.py
eve_netease_api/api/calendar_api.py
eve_netease_api/api/character_api.py
eve_netease_api/api/clones_api.py
eve_netease_api/api/contacts_api.py
eve_netease_api/api/contracts_api.py
eve_netease_api/api/corporation_api.py
eve_netease_api/api/dogma_api.py
eve_netease_api/api/faction_warfare_api.py
eve_netease_api/api/fittings_api.py
eve_netease_api/api/fleets_api.py
eve_netease_api/api/incursions_api.py
eve_netease_api/api/industry_api.py
eve_netease_api/api/insurance_api.py
eve_netease_api/api/killmails_api.py
eve_netease_api/api/location_api.py
eve_netease_api/api/loyalty_api.py
eve_netease_api/api/mail_api.py
eve_netease_api/api/market_api.py
eve_netease_api/api/opportunities_api.py
eve_netease_api/api/planetary_interaction_api.py
eve_netease_api/api/routes_api.py
eve_netease_api/api/search_api.py
eve_netease_api/api/skills_api.py
eve_netease_api/api/sovereignty_api.py
eve_netease_api/api/status_api.py
eve_netease_api/api/universe_api.py
eve_netease_api/api/user_interface_api.py
eve_netease_api/api/wallet_api.py
eve_netease_api/api/wars_api.py
eve_netease_api/models/__init__.py
eve_netease_api/models/bad_request.py
eve_netease_api/models/delete_characters_character_id_mail_labels_label_id_unprocessable_entity.py
eve_netease_api/models/delete_fleets_fleet_id_members_member_id_not_found.py
eve_netease_api/models/delete_fleets_fleet_id_squads_squad_id_not_found.py
eve_netease_api/models/delete_fleets_fleet_id_wings_wing_id_not_found.py
eve_netease_api/models/error_limited.py
eve_netease_api/models/forbidden.py
eve_netease_api/models/gateway_timeout.py
eve_netease_api/models/get_alliances_alliance_id_contacts200_ok.py
eve_netease_api/models/get_alliances_alliance_id_contacts_labels200_ok.py
eve_netease_api-1.17.0.dist-info/METADATA
eve_netease_api-1.17.0.dist-info/WHEEL
eve_netease_api-1.17.0.dist-info/top_level.txt
eve_netease_api-1.17.0.dist-info/RECORD
